pypoolstation/__init__.py
pypoolstation-0.5.8.dist-info/LICENSE
pypoolstation-0.5.8.dist-info/METADATA
pypoolstation-0.5.8.dist-info/WHEEL
pypoolstation-0.5.8.dist-info/RECORD
