Metadata-Version: 2.1
Name: pypoolstation
Version: 0.5.8
Summary: Python library to interact with the API of the Poolstation (https://poolstation.net) domotic platform for pool equipment
License: MIT
Author: cibernox
Author-email: miguel.camba@gmail.com
Requires-Python: >=3.10,<4.0
Classifier: License :: OSI Approved :: MIT License
Classifier: Programming Language :: Python :: 3
Classifier: Programming Language :: Python :: 3.10
Classifier: Programming Language :: Python :: 3.11
Requires-Dist: aiohttp (>=3.8.4,<4.0.0)
